<document ID-DOI="http://doi.org/10.5281/zenodo.3795866" ID-GBIF-Dataset="6110e21e-b367-41ab-98f4-14b4b437c1c3" ID-GBIF-Taxon="163877497" ID-ISSN="1734-1833" ID-Zenodo-Dep="3795866" checkinTime="1588191590610" checkinUser="felipe" docAuthor="Jin, Mengjie, Keyzer, Roger De, Hutchinson, Paul, Pang, Hong &amp; Ślipiński, Adam" docDate="2020" docId="03ED87B7CB6A1B30F94EF999FB1BFA1D" docLanguage="en" docName="AnnalesZoologici.70.1.33-96.pdf.imf" docOrigin="Annales Zoologici 70 (1)" docStyle="DocumentStylede.uka.ipd.idaho.easyIO.settings.Settings@7953c5c6" docStyleName="annaleszoologici.2020.journal_article" docTitle="Hagrides mandibularis Jin &amp; Keyzer &amp; Hutchinson &amp; Pang &amp; Ślipiński 2020, sp. nov." docType="treatment" docVersion="4" lastPageNumber="63" masterDocId="FFD4FFCFCB741B2EF845FFA6FFE9FFC6" masterDocTitle="A Review Of The Australian Macrotomini (Coleoptera: Cerambycidae: Prioninae)" masterLastPageNumber="96" masterPageNumber="33" pageId="30" pageNumber="63" updateTime="1643441399192" updateUser="ExternalLinkService" zenodo-license-document="CLOSED">
<mods:mods xmlns:mods="http://www.loc.gov/mods/v3">
<mods:titleInfo>
<mods:title>A Review Of The Australian Macrotomini (Coleoptera: Cerambycidae: Prioninae)</mods:title>
</mods:titleInfo>
<mods:name type="personal">
<mods:role>
<mods:roleTerm>Author</mods:roleTerm>
</mods:role>
<mods:namePart>Jin, Mengjie</mods:namePart>
<mods:affiliation>State Key Laboratory of Biocontrol, School of Life Sciences / School of Ecology, Sun Yat-Sen University, Guangzhou 510275, China</mods:affiliation>
</mods:name>
<mods:name type="personal">
<mods:role>
<mods:roleTerm>Author</mods:roleTerm>
</mods:role>
<mods:namePart>Keyzer, Roger De</mods:namePart>
<mods:affiliation>Research Associate, Entomology, Australian Museum, 1 William Street, Sydney, NSW 2010, Australia</mods:affiliation>
</mods:name>
<mods:name type="personal">
<mods:role>
<mods:roleTerm>Author</mods:roleTerm>
</mods:role>
<mods:namePart>Hutchinson, Paul</mods:namePart>
<mods:affiliation>Quarantine WA, Department of Primary Industries and Regional Development, Level 1, 24 Fricker Road, Perth Airport, WA 6105, Australia</mods:affiliation>
</mods:name>
<mods:name type="personal">
<mods:role>
<mods:roleTerm>Author</mods:roleTerm>
</mods:role>
<mods:namePart>Pang, Hong</mods:namePart>
<mods:affiliation>State Key Laboratory of Biocontrol, School of Life Sciences / School of Ecology, Sun Yat-Sen University, Guangzhou 510275, China</mods:affiliation>
</mods:name>
<mods:name type="personal">
<mods:role>
<mods:roleTerm>Author</mods:roleTerm>
</mods:role>
<mods:namePart>Ślipiński, Adam</mods:namePart>
<mods:affiliation>Australian National Insect Collection, CSIRO, GPO Box 1700, Canberra, ACT 2601, Australia; adam. slipinski @ csiro. au</mods:affiliation>
</mods:name>
<mods:typeOfResource>text</mods:typeOfResource>
<mods:relatedItem type="host">
<mods:titleInfo>
<mods:title>Annales Zoologici</mods:title>
</mods:titleInfo>
<mods:part>
<mods:date>2020</mods:date>
<mods:detail type="pubDate">
<mods:number>2020-03-30</mods:number>
</mods:detail>
<mods:detail type="volume">
<mods:number>70</mods:number>
</mods:detail>
<mods:detail type="issue">
<mods:number>1</mods:number>
</mods:detail>
<mods:extent unit="page">
<mods:start>33</mods:start>
<mods:end>96</mods:end>
</mods:extent>
</mods:part>
</mods:relatedItem>
<mods:classification>journal article</mods:classification>
<mods:identifier type="DOI">10.3161/00034541ANZ2020.70.1.003</mods:identifier>
<mods:identifier type="GBIF-Dataset">6110e21e-b367-41ab-98f4-14b4b437c1c3</mods:identifier>
<mods:identifier type="ISSN">1734-1833</mods:identifier>
<mods:identifier type="Zenodo-Dep">3776678</mods:identifier>
</mods:mods>
<treatment ID-DOI="http://doi.org/10.5281/zenodo.3795866" ID-GBIF-Taxon="163877497" ID-Zenodo-Dep="3795866" LSID="urn:lsid:plazi:treatment:03ED87B7CB6A1B30F94EF999FB1BFA1D" httpUri="http://treatment.plazi.org/id/03ED87B7CB6A1B30F94EF999FB1BFA1D" lastPageNumber="63" pageId="30" pageNumber="63">
<subSubSection box="[267,648,1599,1621]" pageId="30" pageNumber="63" type="nomenclature">
<paragraph blockId="30.[267,648,1599,1653]" box="[267,648,1599,1621]" pageId="30" pageNumber="63">
<heading box="[267,648,1599,1621]" centered="true" fontSize="9" level="2" pageId="30" pageNumber="63" reason="2">
<taxonomicName authority="Jin &amp; Keyzer &amp; Hutchinson &amp; Pang &amp; Ślipiński, 2020" authorityName="Jin &amp; Keyzer &amp; Hutchinson &amp; Pang &amp; Ślipiński" authorityYear="2020" box="[267,553,1599,1621]" class="Insecta" family="Cerambycidae" genus="Hagrides" kingdom="Animalia" order="Coleoptera" pageId="30" pageNumber="63" phylum="Arthropoda" rank="species" species="mandibularis" status="sp. nov.">
<emphasis bold="true" box="[267,553,1599,1621]" italics="true" pageId="30" pageNumber="63">Hagrides mandibularis</emphasis>
</taxonomicName>
<taxonomicNameLabel box="[560,648,1600,1621]" pageId="30" pageNumber="63" rank="species">sp. nov.</taxonomicNameLabel>
</heading>
</paragraph>
</subSubSection>
<subSubSection box="[362,552,1631,1653]" pageId="30" pageNumber="63" type="description">
<paragraph blockId="30.[267,648,1599,1653]" box="[362,552,1631,1653]" pageId="30" pageNumber="63">
(
<figureCitation box="[371,448,1631,1653]" captionStart="Figure 9" captionStartId="54.[144,203,1859,1876]" captionTargetBox="[150,1421,191,1765]" captionTargetId="figure@54.[150,1435,178,1765]" captionTargetPageId="54" captionText="Figure 9. Hagrides spp. A–E: H. blackburni (Lameere); F–I: H. mandibularis sp. nov.; J–M: H. princeps (Gahan). A, F, J: male, dorsal; B, G, K: male, ventral; C, H, L: female, dorsal; D, M: male, abdominal ventrites 3–5, arrows indicate the transverse elevations; E, I: male mouthparts, dorsal." figureDoi="http://doi.org/10.5281/zenodo.3776698" httpUri="https://zenodo.org/record/3776698/files/figure.png" pageId="30" pageNumber="63">Figs. 9</figureCitation>
F–I, 
<figureCitation box="[500,544,1631,1653]" captionStart="Figure 17" captionStartId="62.[524,583,1884,1901]" captionTargetBox="[173,1426,231,1804]" captionTargetId="figure@62.[151,1436,217,1804]" captionTargetPageId="62" captionText="Figure 17. Distribution maps based on specimens examined." figureDoi="http://doi.org/10.5281/zenodo.3776714" httpUri="https://zenodo.org/record/3776714/files/figure.png" pageId="30" pageNumber="63">17F</figureCitation>
)
</paragraph>
</subSubSection>
<subSubSection pageId="30" pageNumber="63" type="diagnosis">
<paragraph blockId="30.[144,772,1693,1901]" lastBlockId="30.[816,1444,180,1499]" pageId="30" pageNumber="63">
<emphasis bold="true" box="[181,312,1693,1714]" pageId="30" pageNumber="63">
<emphasis bold="true" box="[181,305,1693,1714]" italics="true" pageId="30" pageNumber="63">Diagnosis</emphasis>
.
</emphasis>
<taxonomicName authorityName="Jin &amp; Keyzer &amp; Hutchinson &amp; Pang &amp; Ślipiński" authorityYear="2020" box="[329,552,1693,1715]" class="Insecta" family="Cerambycidae" genus="Hagrides" kingdom="Animalia" order="Coleoptera" pageId="30" pageNumber="63" phylum="Arthropoda" rank="species" species="mandibularis">
<emphasis box="[329,552,1693,1715]" italics="true" pageId="30" pageNumber="63">H. mandibularis</emphasis>
</taxonomicName>
is similar to 
<taxonomicName class="Insecta" family="Cerambycidae" genus="Cnemoplites" kingdom="Animalia" order="Coleoptera" pageId="30" pageNumber="63" phylum="Arthropoda" rank="species" species="blackburni">
<emphasis italics="true" pageId="30" pageNumber="63">H. blackburni</emphasis>
</taxonomicName>
but can be recognised by having longer mandibles (
<figureCitation box="[275,351,1755,1777]" captionStart="Figure 9" captionStartId="54.[144,203,1859,1876]" captionTargetBox="[150,1421,191,1765]" captionTargetId="figure@54.[150,1435,178,1765]" captionTargetPageId="54" captionText="Figure 9. Hagrides spp. A–E: H. blackburni (Lameere); F–I: H. mandibularis sp. nov.; J–M: H. princeps (Gahan). A, F, J: male, dorsal; B, G, K: male, ventral; C, H, L: female, dorsal; D, M: male, abdominal ventrites 3–5, arrows indicate the transverse elevations; E, I: male mouthparts, dorsal." figureDoi="http://doi.org/10.5281/zenodo.3776698" httpUri="https://zenodo.org/record/3776698/files/figure.png" pageId="30" pageNumber="63">Fig. 9I</figureCitation>
), the male abdominal ventrite 5 without transverse elevations at base, the tegmen with shorter parameres. A female is diagnosed by having the ovipositor with shorter distal gonocoxites. It can be separated from 
<taxonomicName authorityName="Gahan, Y" authorityYear="1893" box="[343,497,1880,1901]" class="Insecta" family="Cerambycidae" genus="Cnemoplites" kingdom="Animalia" order="Coleoptera" pageId="30" pageNumber="63" phylum="Arthropoda" rank="species" species="princeps">
<emphasis box="[343,497,1880,1901]" italics="true" pageId="30" pageNumber="63">H. princeps</emphasis>
</taxonomicName>
by having completely punctate pronotal disc, smaller sexual patches on abdominal ventrites, and the tegmen with very short parameres and basal triangular projection. A female can be separated by the rounded distal gonocoxal apices.
</paragraph>
</subSubSection>
<subSubSection pageId="30" pageNumber="63" type="description">
<paragraph blockId="30.[816,1444,180,1499]" pageId="30" pageNumber="63">
<emphasis bold="true" box="[854,1084,334,355]" pageId="30" pageNumber="63">
<emphasis bold="true" box="[854,998,334,355]" italics="true" pageId="30" pageNumber="63">Description</emphasis>
. Male.
</emphasis>
Body length 
<quantity box="[1248,1371,334,356]" metricMagnitude="-2" metricUnit="m" metricValue="4.1" metricValueMax="5.2" metricValueMin="3.0" pageId="30" pageNumber="63" unit="mm" value="41.0" valueMax="52.0" valueMin="30.0">30–52 mm</quantity>
. Body sub-parallel, slightly convex; head weakly transverse; mandibles longer than eye length; pronotum as long as head capsule and pronotal width 1.5× of head width; elytra over 4× longer than pronotum. Antennal scape about 1.5× of antennomere 3 length; interorbital width over 1.2× of eye length. Prosternal process width about the same as hypomeron width and 0.7× length of procoxal cavity; mesoventral process as broad as prosternal process. Abdominal ventrites 1 and 5 longer than the others; ventrite 5 emarginate apically. Metatarsomeres 1–3 equal in length, tarsomere 5 shorter than 1–3 combined. 
<emphasis bold="true" box="[987,1085,705,726]" pageId="30" pageNumber="63">Female.</emphasis>
Body length 
<quantity box="[1236,1355,705,727]" metricMagnitude="-2" metricUnit="m" metricValue="6.5" metricValueMax="8.0" metricValueMin="5.0" pageId="30" pageNumber="63" unit="mm" value="65.0" valueMax="80.0" valueMin="50.0">50–80 mm</quantity>
.
</paragraph>
</subSubSection>
<subSubSection pageId="30" pageNumber="63" type="etymology">
<paragraph blockId="30.[816,1444,180,1499]" pageId="30" pageNumber="63">
<emphasis bold="true" box="[854,990,735,757]" pageId="30" pageNumber="63">
<emphasis bold="true" box="[854,983,735,757]" italics="true" pageId="30" pageNumber="63">Etymology</emphasis>
.
</emphasis>
The species name emphasises its elongate mandibles, which is a distinctive character to separate it from the morphologically similar species.
</paragraph>
<paragraph blockId="30.[816,1444,180,1499]" pageId="30" pageNumber="63">
<emphasis bold="true" box="[854,934,828,850]" pageId="30" pageNumber="63">
<emphasis bold="true" box="[854,927,829,850]" italics="true" pageId="30" pageNumber="63">Types</emphasis>
.
</emphasis>
<materialsCitation ID-GBIF-Occurrence="2609452932" collectingDate="2015-01-13" collectionCode="ANIC" collectorName="W. Menzies &amp; P. Hutchinson" pageId="30" pageNumber="63" specimenCode="ANIC 25- 066034" specimenCount="1" typeStatus="holotype">
<emphasis bold="true" box="[940,1082,828,850]" pageId="30" pageNumber="63">
<typeStatus box="[940,1051,828,849]" pageId="30" pageNumber="63">Holotype</typeStatus>
. ♂
</emphasis>
“WA: 
<quantity box="[1153,1215,828,850]" metricMagnitude="4" metricUnit="m" metricValue="1.0" pageId="30" pageNumber="63" unit="km" value="10.0">10km</quantity>
<collectorName box="[1221,1353,828,850]" pageId="30" pageNumber="63">W. Menzies</collectorName>
, 
<date pageId="30" pageNumber="63" value="2015-01-13">
<collectingDate pageId="30" pageNumber="63" value="2015-01-13">13 Jan. 2015</collectingDate>
</date>
, 4000w MV Light, 
<collectorName box="[1117,1287,859,881]" pageId="30" pageNumber="63">P. Hutchinson</collectorName>
| 
<specimenCode collectionCode="ANIC" country="Australia" httpUri="http://biocol.org/urn:lsid:biocol.org:col:32981" lsid="urn:lsid:biocol.org:col:32981" name="Australian National Insect Collection" pageId="30" pageNumber="63">ANIC 25- 066034</specimenCode>
” (
<collectionCode box="[928,994,890,912]" country="Australia" httpUri="http://biocol.org/urn:lsid:biocol.org:col:32981" lsid="urn:lsid:biocol.org:col:32981" name="Australian National Insect Collection" pageId="30" pageNumber="63">ANIC</collectionCode>
)
</materialsCitation>
. 
<materialsCitation ID-GBIF-Occurrence="2609453019" collectingDate="2017-02-02" collectionCode="ASC" collectorName="Allen M. Sundholm" elevation="426" latitude="-29.621574" location="Lake Barlee-Youanmi Road." longLatPrecision="1" longitude="119.28648" pageId="30" pageNumber="63" specimenCount="1" typeStatus="paratype">
<emphasis bold="true" box="[1023,1205,890,912]" pageId="30" pageNumber="63">
<typeStatus box="[1023,1148,890,911]" pageId="30" pageNumber="63">Paratypes</typeStatus>
(5).
</emphasis>
2 
<emphasis bold="true" box="[1233,1272,890,912]" pageId="30" pageNumber="63">♂♂</emphasis>
: “WA: 
<date pageId="30" pageNumber="63" value="2017-02-02">
<collectingDate pageId="30" pageNumber="63" value="2017-02-02">2 Feb. 2017</collectingDate>
</date>
, 
<location LSID="urn:lsid:plazi:treatment:03ED87B7CB6A1B30F94EF999FB1BFA1D:8E9B607ACB6A1B30FB3EFC3FFB39FC69" box="[891,1232,921,943]" latitude="-29.621574" longLatPrecision="1" longitude="119.28648" name="Lake Barlee-Youanmi Road." pageId="30" pageNumber="63">Lake Barlee-Youanmi Road.</location>
, 
<locationDeviation location="Diemels Homestead." pageId="30" pageNumber="63">
<quantity box="[1251,1334,921,943]" metricMagnitude="3" metricUnit="m" metricValue="5.43" pageId="30" pageNumber="63" unit="km" value="5.43">5.43km</quantity>
NNW of Diemels Homestead.
</locationDeviation>
<geoCoordinate box="[1055,1211,952,974]" degrees="29" direction="south" minutes="37" orientation="latitude" pageId="30" pageNumber="63" precision="1" seconds="17.67" value="-29.621574">29°37’17.67’’S</geoCoordinate>
<geoCoordinate box="[1217,1390,952,974]" degrees="119" direction="east" minutes="17" orientation="longitude" pageId="30" pageNumber="63" precision="1" seconds="11.35" value="119.28648">119°17’11.35’’E</geoCoordinate>
, Elv. 
<quantity box="[816,880,983,1005]" metricMagnitude="2" metricUnit="m" metricValue="4.26" pageId="30" pageNumber="63" unit="m" value="426.0">
<elevation box="[816,880,983,1005]" metricMagnitude="2" metricUnit="m" metricValue="4.26" pageId="30" pageNumber="63" unit="m" value="426.0">426m</elevation>
</quantity>
, attracted to 250w MV Light, 
<collectorName box="[1220,1440,983,1005]" pageId="30" pageNumber="63">Allen M. Sundholm</collectorName>
, Joe Bugeja” (
<collectionCode box="[967,1023,1014,1036]" pageId="30" pageNumber="63">ASC</collectionCode>
)
</materialsCitation>
; 
<materialsCitation ID-GBIF-Occurrence="2609452667" collectingDate="1989-01-13" collectionCode="AM" collectorName="M. S. and B. J. Moulds" elevation="426" isTailEnumeration="true" latitude="-29.621574" location="Lake Douglas" longLatPrecision="1" longitude="119.28648" pageId="30" pageNumber="63" specimenCount="1" typeStatus="paratype">
“WA: 
<location LSID="urn:lsid:plazi:treatment:03ED87B7CB6A1B30F94EF999FB1BFA1D:8E9B607ACB6A1B30FC11FC53FB1AFBCD" box="[1108,1267,1013,1035]" name="Lake Douglas" pageId="30" pageNumber="63">Lake Douglas</location>
, 
<locationDeviation location="Kalgoorlie" pageId="30" pageNumber="63">
<quantity box="[1278,1340,1013,1035]" metricMagnitude="4" metricUnit="m" metricValue="1.2" pageId="30" pageNumber="63" unit="km" value="12.0">12km</quantity>
S of Kalgoorlie
</locationDeviation>
, 
<date box="[917,1078,1044,1066]" pageId="30" pageNumber="63" value="1989-01-13">
<collectingDate box="[917,1078,1044,1066]" pageId="30" pageNumber="63" value="1989-01-13">13 Jan. 1989</collectingDate>
</date>
, 
<collectorName box="[1097,1362,1044,1066]" pageId="30" pageNumber="63">M.S. and B.J. Moulds</collectorName>
| AM K503085” (
<collectionCode box="[941,987,1075,1097]" country="Australia" name="Australian Museum" pageId="30" pageNumber="63" type="Museum">AM</collectionCode>
)
</materialsCitation>
; 
<materialsCitation ID-GBIF-Occurrence="2609453027" collectingDate="2015-01-13" collectionCode="ANIC" collectorName="W. Menzies" pageId="30" pageNumber="63" specimenCode="ANIC 25- 066004" specimenCount="1" typeStatus="paratype">
3 
<emphasis bold="true" box="[1020,1059,1075,1097]" pageId="30" pageNumber="63">♀♀</emphasis>
: “WA: 
<quantity box="[1142,1204,1075,1097]" metricMagnitude="4" metricUnit="m" metricValue="1.0" pageId="30" pageNumber="63" unit="km" value="10.0">10km</quantity>
<collectorName box="[1213,1348,1075,1097]" pageId="30" pageNumber="63">W. Menzies</collectorName>
, 
<date pageId="30" pageNumber="63" value="2015-01-13">
<collectingDate pageId="30" pageNumber="63" value="2015-01-13">13 Jan. 2015</collectingDate>
</date>
, 4000w MV Light, P. Hutchinson | 
<specimenCode collectionCode="ANIC" country="Australia" httpUri="http://biocol.org/urn:lsid:biocol.org:col:32981" lsid="urn:lsid:biocol.org:col:32981" name="Australian National Insect Collection" pageId="30" pageNumber="63">ANIC 25- 066004</specimenCode>
” (
<collectionCode box="[927,995,1137,1159]" country="Australia" httpUri="http://biocol.org/urn:lsid:biocol.org:col:32981" lsid="urn:lsid:biocol.org:col:32981" name="Australian National Insect Collection" pageId="30" pageNumber="63">ANIC</collectionCode>
)
</materialsCitation>
; 
<materialsCitation ID-GBIF-Occurrence="2609452999" collectingDate="1969-01" collectionCode="ANIC" collectorName="W. Menzies" isTailEnumeration="true" pageId="30" pageNumber="63" specimenCode="ANIC 25-072811" specimenCount="10" typeStatus="paratype">
“ 
<specimenCount box="[1031,1095,1137,1158]" pageId="30" pageNumber="63" type="generic">10 N.</specimenCount>
Rawlinna, WA, 
<date box="[1297,1407,1137,1159]" pageId="30" pageNumber="63" value="1969-01">
<collectingDate box="[1297,1407,1137,1159]" pageId="30" pageNumber="63" value="1969-01">Jan 1969</collectingDate>
</date>
, J. Bywater | 
<specimenCode box="[942,1125,1168,1190]" collectionCode="ANIC" country="Australia" httpUri="http://biocol.org/urn:lsid:biocol.org:col:32981" lsid="urn:lsid:biocol.org:col:32981" name="Australian National Insect Collection" pageId="30" pageNumber="63">ANIC 25-072811</specimenCode>
” (
<collectionCode box="[1151,1219,1168,1190]" country="Australia" httpUri="http://biocol.org/urn:lsid:biocol.org:col:32981" lsid="urn:lsid:biocol.org:col:32981" name="Australian National Insect Collection" pageId="30" pageNumber="63">ANIC</collectionCode>
)
</materialsCitation>
; 
<materialsCitation ID-GBIF-Occurrence="2609452939" collectingDate="2017-02-01" collectionCode="ASC" collectorName="Allen M. Sundholm" elevation="426" latitude="-29.621574" location="Lake Barlee-Youanmi Road." longLatPrecision="1" longitude="119.28648" pageId="30" pageNumber="63" specimenCount="1" typeStatus="paratype">
“WA: 
<date box="[1305,1439,1168,1190]" pageId="30" pageNumber="63" value="2017-02-01">
<collectingDate box="[1305,1439,1168,1190]" pageId="30" pageNumber="63" value="2017-02-01">1 Feb. 2017</collectingDate>
</date>
, 
<location LSID="urn:lsid:plazi:treatment:03ED87B7CB6A1B30F94EF999FB1BFA1D:8E9B607ACB6A1B30FB75FB09FB92FB03" box="[816,1147,1199,1221]" latitude="-29.621574" longLatPrecision="1" longitude="119.28648" name="Lake Barlee-Youanmi Road." pageId="30" pageNumber="63">Lake Barlee-Youanmi Road.</location>
, 
<locationDeviation location="Diemels Homestead." pageId="30" pageNumber="63">
<quantity box="[1161,1243,1199,1221]" metricMagnitude="3" metricUnit="m" metricValue="5.43" pageId="30" pageNumber="63" unit="km" value="5.43">5.43km</quantity>
NNW of Diemels Homestead.
</locationDeviation>
<geoCoordinate box="[964,1120,1230,1252]" degrees="29" direction="south" minutes="37" orientation="latitude" pageId="30" pageNumber="63" precision="1" seconds="17.67" value="-29.621574">29°37’17.67’’S</geoCoordinate>
<geoCoordinate box="[1132,1305,1229,1251]" degrees="119" direction="east" minutes="17" orientation="longitude" pageId="30" pageNumber="63" precision="1" seconds="11.35" value="119.28648">119°17’11.35’’E</geoCoordinate>
, Elv. 
<quantity box="[1376,1440,1230,1252]" metricMagnitude="2" metricUnit="m" metricValue="4.26" pageId="30" pageNumber="63" unit="m" value="426.0">
<elevation box="[1376,1440,1230,1252]" metricMagnitude="2" metricUnit="m" metricValue="4.26" pageId="30" pageNumber="63" unit="m" value="426.0">426m</elevation>
</quantity>
, attracted to 250w MV Light, 
<collectorName box="[1162,1390,1260,1282]" pageId="30" pageNumber="63">Allen M. Sundholm</collectorName>
, Joe Bugeja” (
<collectionCode box="[922,978,1291,1313]" pageId="30" pageNumber="63">ASC</collectionCode>
)
</materialsCitation>
;
</paragraph>
<paragraph blockId="30.[816,1444,180,1499]" pageId="30" pageNumber="63">
<emphasis bold="true" box="[854,1176,1322,1344]" italics="true" pageId="30" pageNumber="63">Other material examined</emphasis>
(
<figureCitation box="[1196,1296,1322,1344]" captionStart="Figure 17" captionStartId="62.[524,583,1884,1901]" captionTargetBox="[173,1426,231,1804]" captionTargetId="figure@62.[151,1436,217,1804]" captionTargetPageId="62" captionText="Figure 17. Distribution maps based on specimens examined." figureDoi="http://doi.org/10.5281/zenodo.3776714" httpUri="https://zenodo.org/record/3776714/files/figure.png" pageId="30" pageNumber="63">Fig. 17F</figureCitation>
). 
<materialsCitation ID-GBIF-Occurrence="2609452790" collectingDate="2015-01-13" collectionCode="ANIC" collectorName="W. Menzies &amp; Hutchinson, P" country="Australia" location="Western Australia" pageId="30" pageNumber="63" specimenCount="1" stateProvince="Western Australia">
<emphasis bold="true" pageId="30" pageNumber="63">
<collectingCountry box="[1323,1439,1322,1344]" name="Australia" pageId="30" pageNumber="63">Australia</collectingCountry>
: MV
</emphasis>
(1 
<emphasis bold="true" box="[893,913,1353,1375]" pageId="30" pageNumber="63">♀</emphasis>
): [no data]. 
<emphasis bold="true" box="[1068,1384,1353,1375]" pageId="30" pageNumber="63">
<collectingRegion box="[1068,1302,1353,1375]" country="Australia" name="Western Australia" pageId="30" pageNumber="63">Western Australia</collectingRegion>
: 
<collectionCode box="[1319,1384,1353,1375]" country="Australia" httpUri="http://biocol.org/urn:lsid:biocol.org:col:32981" lsid="urn:lsid:biocol.org:col:32981" name="Australian National Insect Collection" pageId="30" pageNumber="63">ANIC</collectionCode>
</emphasis>
(1 
<emphasis bold="true" box="[1417,1437,1353,1375]" pageId="30" pageNumber="63">♂</emphasis>
; 1 
<emphasis bold="true" box="[830,850,1384,1406]" pageId="30" pageNumber="63">♀</emphasis>
): 2: 
<quantity box="[900,962,1384,1406]" metricMagnitude="4" metricUnit="m" metricValue="1.0" pageId="30" pageNumber="63" unit="km" value="10.0">10km</quantity>
<collectorName box="[969,1102,1384,1406]" pageId="30" pageNumber="63">W. Menzies</collectorName>
, 
<date box="[1114,1258,1384,1406]" pageId="30" pageNumber="63" value="2015-01-13">
<collectingDate box="[1114,1258,1384,1406]" pageId="30" pageNumber="63" value="2015-01-13">13 Jan. 2015</collectingDate>
</date>
, 
<collectorName box="[1270,1435,1384,1406]" pageId="30" pageNumber="63">Hutchinson, P</collectorName>
</materialsCitation>
.; 
<materialsCitation ID-GBIF-Occurrence="2609452713" box="[816,1095,1415,1437]" collectionCode="XX" collectorName="Marvel Loch" country="Australia" pageId="30" pageNumber="63" specimenCount="1">
<emphasis bold="true" box="[816,858,1415,1436]" pageId="30" pageNumber="63">MV</emphasis>
(2 
<emphasis bold="true" box="[888,927,1415,1437]" pageId="30" pageNumber="63">
<collectionCode box="[888,927,1415,1437]" pageId="30" pageNumber="63">♀♀</collectionCode>
</emphasis>
): 
<collectorName box="[951,1095,1415,1437]" pageId="30" pageNumber="63">Marvel Loch</collectorName>
</materialsCitation>
; 
<materialsCitation ID-GBIF-Occurrence="2609453100" box="[1107,1423,1415,1437]" collectorName="Douglas, A" country="Australia" location="Rottnest Island" pageId="30" pageNumber="63" specimenCount="1">
<location LSID="urn:lsid:plazi:treatment:03ED87B7CB6A1B30F94EF999FB1BFA1D:8E9B607ACB6A1B30FC16FA21FAECFA5B" box="[1107,1285,1415,1437]" country="Australia" name="Rottnest Island" pageId="30" pageNumber="63">Rottnest Island</location>
, 
<collectorName box="[1296,1423,1415,1437]" pageId="30" pageNumber="63">Douglas, A</collectorName>
</materialsCitation>
.
</paragraph>
<paragraph blockId="30.[816,1444,180,1499]" pageId="30" pageNumber="63">
<emphasis bold="true" box="[854,1059,1445,1467]" pageId="30" pageNumber="63">
<emphasis bold="true" box="[854,1052,1445,1467]" italics="true" pageId="30" pageNumber="63">Molecular data</emphasis>
.
</emphasis>
BioSample ID: SAMN12650095 (
<typeStatus box="[824,932,1477,1499]" pageId="30" pageNumber="63">Holotype</typeStatus>
); SAMN12650096 (
<typeStatus box="[1144,1254,1477,1499]" pageId="30" pageNumber="63">Paratype</typeStatus>
).
</paragraph>
</subSubSection>
</treatment>
</document>