<document id="09A32CF600E3D34B94422E0F06682650" ID-DOI="http://doi.org/10.5281/zenodo.5679007" ID-GBIF-Dataset="fb1edc8f-194a-4d37-b2f2-6a596e8e613d" ID-GBIF-Taxon="119400063" ID-ISSN="1175-5326" ID-Zenodo-Dep="5679007" _generate="added" checkinTime="1460302849089" checkinUser="plazi" docAuthor="Rivera, Julio" docDate="2010" docId="03BEDA61225BEB607FF966B2FB846784" docLanguage="en" docName="zt02638p064.pdf" docOrigin="Zootaxa 2638" docStyle="DocumentStylede.uka.ipd.idaho.easyIO.settings.Settings@59939293" docStyleName="zootaxa.2007.journal_article" docTitle="Hymenopodidae" docType="treatment" docVersion="10" lastPageNumber="52" masterDocId="FF87A2192253EB687F6E6625FFC6660B" masterDocTitle="A historical review of praying mantid taxonomy and systematics in the Neotropical Region: State of knowledge and recent advances (Insecta: Mantodea)" masterLastPageNumber="64" masterPageNumber="44" pageId="8" pageNumber="52" updateTime="1636704911149" updateUser="ExternalLinkService">
<mods:mods id="F498F3A1158D72C325BF96154EDDF9C9" xmlns:mods="http://www.loc.gov/mods/v3">
<mods:titleInfo id="E158E6FB6264E6B552F3FF291FE28CAA">
<mods:title id="177E8D9B2625F434FAFA26413C92FE42">A historical review of praying mantid taxonomy and systematics in the Neotropical Region: State of knowledge and recent advances (Insecta: Mantodea)</mods:title>
</mods:titleInfo>
<mods:name id="8E9A17191EDEA5D630ABAA76CF417E0E" type="personal">
<mods:role id="A472C67810636976773B616E5406D5AE">
<mods:roleTerm id="7D66286385A1EF7A5B697FA3D6C8966A">Author</mods:roleTerm>
</mods:role>
<mods:namePart id="296E7DAEF4F26755CE2D2031EC5658BB">Rivera, Julio</mods:namePart>
</mods:name>
<mods:typeOfResource id="D162CFC25FCB7941C058E24A9161DBFC">text</mods:typeOfResource>
<mods:relatedItem id="C0481E3F365C51D848E03F43F95FDACC" type="host">
<mods:titleInfo id="33537DF98BF6EBC7BDF34393C61E82BA">
<mods:title id="D3D46559C5DCBCC3A4259AE7F183C0CF">Zootaxa</mods:title>
</mods:titleInfo>
<mods:part id="4ADBE3BED322067F262985A1989621D6">
<mods:date id="42152917BE953ECBF1122BD00718C091">2010</mods:date>
<mods:detail id="EED9AFE6AF930111D0F0ED3E62605B89" type="volume">
<mods:number id="326F2B2571DF3DE1441C9467E5D17383">2638</mods:number>
</mods:detail>
<mods:extent id="CBC4DF02A4D73C8169DC33DC113DFB11" unit="page">
<mods:start id="50785E4361AF6FF03C4AC4A979D69E25">44</mods:start>
<mods:end id="031F024639B91C92E41B34D23FC28C32">64</mods:end>
</mods:extent>
</mods:part>
</mods:relatedItem>
<mods:classification id="27CDC3708D9FC22B2EC5C293C4D9795C">journal article</mods:classification>
<mods:identifier id="42618083EBEF3B34C00F1CB8BC9C0474" type="DOI">10.5281/zenodo.198493</mods:identifier>
<mods:identifier id="025E9FC289E1C39980B6428F81F9A0AE" type="GBIF-Dataset">fb1edc8f-194a-4d37-b2f2-6a596e8e613d</mods:identifier>
<mods:identifier id="F988568190B0F0B50C81264AA5B3CA56" type="ISSN">1175-5326</mods:identifier>
<mods:identifier id="8EF0AA8A0DC426657B413DF97F6541FF" type="Zenodo-Dep">198493</mods:identifier>
</mods:mods>
<treatment id="03BEDA61225BEB607FF966B2FB846784" ID-DOI="http://doi.org/10.5281/zenodo.5679007" ID-GBIF-Taxon="119400063" ID-Zenodo-Dep="5679007" LSID="urn:lsid:plazi:treatment:03BEDA61225BEB607FF966B2FB846784" httpUri="http://treatment.plazi.org/id/03BEDA61225BEB607FF966B2FB846784" lastPageNumber="52" pageId="8" pageNumber="52">
<subSubSection id="C30D38FC225BEB607FF966B2FB846784" pageId="8" pageNumber="52" type="nomenclature">
<paragraph id="8BA86B77225BEB607FF966B2FEA266BA" blockId="8.[151,356,151,177]" box="[151,356,151,177]" pageId="8" pageNumber="52">
<heading id="D0E0DC1B225BEB607FF966B2FEA266BA" bold="true" box="[151,356,151,177]" fontSize="11" level="1" pageId="8" pageNumber="52" reason="1">
<taxonomicName id="4C1710F4225BEB607FF966B2FEA266BA" box="[151,356,151,177]" class="Insecta" family="Hymenopodidae" kingdom="Animalia" order="Mantodea" pageId="8" pageNumber="52" phylum="Arthropoda" rank="family">
<emphasis id="B963B765225BEB607FF966B2FEA266BA" bold="true" box="[151,356,151,177]" pageId="8" pageNumber="52">Hymenopodidae</emphasis>
</taxonomicName>
</heading>
</paragraph>
<paragraph id="8BA86B77225BEB607FF966C5FB846784" blockId="8.[151,1437,224,399]" pageId="8" pageNumber="52">
Only one genus in the subfamily 
<taxonomicName id="4C1710F4225BEB607D4666C5FD1866F1" box="[552,734,224,250]" class="Insecta" family="Hymenopodidae" kingdom="Animalia" order="Mantodea" pageId="8" pageNumber="52" phylum="Arthropoda" rank="subFamily" subFamily="Epaphroditinae">Epaphroditinae</taxonomicName>
occurs in the Neotropics and it is restricted to the Greater Antilles. 
<taxonomicName id="4C1710F4225BEB607E626720FDD26714" authority="Serville" authorityName="Serville" box="[268,532,261,287]" class="Insecta" family="Hymenopodidae" genus="Epaphrodita" kingdom="Animalia" order="Mantodea" pageId="8" pageNumber="52" phylum="Arthropoda" rank="genus">
<emphasis id="B963B765225BEB607E626720FE6F6715" box="[268,425,261,286]" italics="true" pageId="8" pageNumber="52">Epaphrodita</emphasis>
Serville
</taxonomicName>
contains three species: 
<taxonomicName id="4C1710F4225BEB607C2D6720FB7A6714" authority="Beauvois, 1805" authorityName="Beauvois" authorityYear="1805" box="[835,1212,261,287]" class="Insecta" family="Hymenopodidae" genus="Epaphrodita" kingdom="Animalia" order="Mantodea" pageId="8" pageNumber="52" phylum="Arthropoda" rank="species" species="musarum">
<emphasis id="B963B765225BEB607C2D6720FC1C6715" box="[835,986,261,286]" italics="true" pageId="8" pageNumber="52">E. musarum</emphasis>
(Beauvois, 
<number id="3DDF7950225BEB607B1D6720FB756714" box="[1139,1203,261,287]" pageId="8" pageNumber="52" value="1805.0">1805</number>
)
</taxonomicName>
and 
<taxonomicName id="4C1710F4225BEB607B956720FD8F674F" authority="Lombardo &amp; Perez-Gelabert, 2004" authorityName="Lombardo &amp; Perez-Gelabert" authorityYear="2004" class="Insecta" family="Hymenopodidae" genus="Epaphrodita" kingdom="Animalia" order="Mantodea" pageId="8" pageNumber="52" phylum="Arthropoda" rank="species" species="lobivertex">
<emphasis id="B963B765225BEB607B956720FA5B6715" box="[1275,1437,261,286]" italics="true" pageId="8" pageNumber="52">E. lobivertex</emphasis>
<bibRefCitation id="EF861686225BEB607FF9670FFD8F674F" author="Lombardo" box="[151,585,298,324]" pageId="8" pageNumber="52" refString="Lombardo, F. &amp; Perez-Gelabert, D. E. (2004) The mantids of Hispaniola, with the description of two new species (Mantodea). Boletin de la Sociedad Entomologica Aragones a, 34, 35 - 48." type="journal article" year="2004">
Lombardo &amp; Perez-Gelabert, 
<number id="3DDF7950225BEB607D65670FFD8F674F" box="[523,585,298,324]" pageId="8" pageNumber="52" value="2004.0">2004</number>
</bibRefCitation>
</taxonomicName>
are treated by 
<bibRefCitation id="EF861686225BEB607C68670FFB0E674F" author="Lombardo" box="[774,1224,298,324]" pageId="8" pageNumber="52" refString="Lombardo, F. &amp; Perez-Gelabert, D. E. (2004) The mantids of Hispaniola, with the description of two new species (Mantodea). Boletin de la Sociedad Entomologica Aragones a, 34, 35 - 48." type="journal article" year="2004">
Lombardo &amp; Perez-Gelabert (
<number id="3DDF7950225BEB607B15670FFB79674F" box="[1147,1215,298,324]" pageId="8" pageNumber="52" value="2004.0">2004</number>
)
</bibRefCitation>
, and 
<taxonomicName id="4C1710F4225BEB607A65670FFE986761" authority="Saussure, 1870" authorityName="Saussure" authorityYear="1870" class="Insecta" family="Hymenopodidae" genus="Epaphrodita" kingdom="Animalia" order="Mantodea" pageId="8" pageNumber="52" phylum="Arthropoda" rank="species" species="undulata">
<emphasis id="B963B765225BEB607A65670FFA5A6748" box="[1291,1436,298,323]" italics="true" pageId="8" pageNumber="52">E. undulata</emphasis>
(
<bibRefCitation id="EF861686225BEB607FF16775FE906761" author="Saussure" box="[159,342,336,362]" pageId="8" pageNumber="52" refString="Saussure, H. de. (1870) Additions au Systeme des Mantides. Mitteilungen der Schweizerischen entomologischen Gesellschaft, 3 (5), 221 - 244." type="journal article" year="1870">
Saussure, 
<number id="3DDF7950225BEB607E746775FE906761" box="[282,342,336,362]" pageId="8" pageNumber="52" value="1870.0">1870</number>
</bibRefCitation>
)
</taxonomicName>
was revalidated by 
<bibRefCitation id="EF861686225BEB607D206775FD2E6761" author="Roy" box="[590,744,336,362]" pageId="8" pageNumber="52" refString="Roy, R. (2005 a) Epaphrodita undulata (Saussure, 1870) bona species (Dict. Hymenopodidae). Bulletin de la Societe Entomologique de France, 110, 57 - 58." type="journal article" year="2005" yearSuffix="a">
Roy (
<number id="3DDF7950225BEB607DFE6775FD176761" box="[656,721,336,362]" pageId="8" pageNumber="52" value="2005.0">2005</number>
a)
</bibRefCitation>
. General remarks on 
<taxonomicName id="4C1710F4225BEB607C886775FBBD6762" box="[998,1147,336,361]" class="Insecta" family="Hymenopodidae" genus="Epaphrodita" kingdom="Animalia" order="Mantodea" pageId="8" pageNumber="52" phylum="Arthropoda" rank="genus">
<emphasis id="B963B765225BEB607C886775FBBD6762" box="[998,1147,336,361]" italics="true" pageId="8" pageNumber="52">Epaphrodita</emphasis>
</taxonomicName>
can be found in 
<bibRefCitation id="EF861686225BEB607A2B6775FF336784" author="Salazar" pageId="8" pageNumber="52" refString="Salazar, J. A. (2004 a) Epaphrodita Serville; Stenophylla Westwood y Acanthops Serville, tres generos de mantidos hoja-seca de la region Neotropical (Mantodea). Boletin Cientifico del Museo de Historia Natural Universidad de Caldas, 8, 211 - 221." type="journal article" year="2004" yearSuffix="a">
Salazar (
<number id="3DDF7950225BEB607FF16750FF196784" box="[159,223,373,399]" pageId="8" pageNumber="52" value="2004.0">2004</number>
a)
</bibRefCitation>
. The inclusion of this genus within the 
<taxonomicName id="4C1710F4225BEB607DAC6750FC426784" box="[706,900,373,399]" class="Insecta" family="Hymenopodidae" kingdom="Animalia" order="Mantodea" pageId="8" pageNumber="52" phylum="Arthropoda" rank="family">Hymenopodidae</taxonomicName>
is questionable.
</paragraph>
</subSubSection>
</treatment>
</document>