<document id="C0C3423B29E919B0034213D2AD7619A7" ID-DOI="10.5281/zenodo.292251" ID-ISBN="3-7643-0527-4" ID-Zenodo-Dep="292251" checkinTime="1646762443207" checkinUser="donat" docAuthor="Hess, Hans Ernst, Landolt, Elias &amp; Hirzel, Rosmarie" docDate="1976" docId="3A98448511120A61030B91D0991889D3" docLanguage="de" docName="euphorbiaceae.xml" docOrigin="Birkhaeuser Verlag" docSource="https://doi.org/10.5281/zenodo.292251" docTitle="Euphorbia falcata L." docType="treatment" docVersion="2" lastPageNumber="669" masterDocId="FFFBB32C6E684D66B6D4A7265A39A269" masterDocTitle="Flora der Schweiz und angrenzender Gebiete. Band 2. Nymphaceae bis Primulaceae (2 nd edition) (p. 956): Euphorbiaceae" pageId="null" pageNumber="669" sec="euphorbiaceae.s38" updateTime="1647483367614" updateUser="donat">
<mods:mods id="753FA6E4428FB366CBBF398D64AA73E6" xmlns:mods="http://www.loc.gov/mods/v3">
<mods:titleInfo id="8721B5C10C3757F5FB852FF41B5C05DB">
<mods:title id="782164321988762F0D019592A001951B">Flora der Schweiz und angrenzender Gebiete. Band 2. Nymphaceae bis Primulaceae (2 nd edition) (p. 956): Euphorbiaceae</mods:title>
</mods:titleInfo>
<mods:name id="49F49BB69711E3E25B94787E773772D5" type="personal">
<mods:role id="882BFB9AE7DE77786E8DF8F66E04A8A7">
<mods:roleTerm id="C23C9C4DF500C895A6A73D8148C8A0EC">Author</mods:roleTerm>
</mods:role>
<mods:namePart id="7EFFF05CB0D67E1AF1E1B829BD875A56">Hess, Hans Ernst</mods:namePart>
</mods:name>
<mods:name id="0FB8C918F27884B6B77CF10A5029DC63" type="personal">
<mods:role id="8D042926ABD7E1A974DBDD62EA0C036E">
<mods:roleTerm id="35EC761482A8572B438466AB8B1F2077">Author</mods:roleTerm>
</mods:role>
<mods:namePart id="F97F87BD1534642805FE84DFDE37AEBE">Landolt, Elias</mods:namePart>
</mods:name>
<mods:name id="1B329CC6A09B1F459900FA75BAFD706A" type="personal">
<mods:role id="2ECACB8F30A5DCB5F4A1761A76DA0D7E">
<mods:roleTerm id="29ADDADE17E219BA7AD00F357A0A9445">Author</mods:roleTerm>
</mods:role>
<mods:namePart id="844F29D46A1D7034ED4F3E8600C3B86D">Hirzel, Rosmarie</mods:namePart>
</mods:name>
<mods:typeOfResource id="AFA0380CB9D2E8BECAA170101A0546E6">text</mods:typeOfResource>
<mods:originInfo id="EE2ACECD85C03A442DA4BAF02E1D0A5C">
<mods:dateIssued id="0487DEDD043A29246F52224CF706CB0D">1976</mods:dateIssued>
<mods:publisher id="D21FD64194F5733AED05438853D7C6B0">Birkhaeuser Verlag</mods:publisher>
</mods:originInfo>
<mods:location id="FB172A3669D11A88570C13715CA86113">
<mods:url id="9DC364797CB94D91937AA2E94D625672">https://doi.org/10.5281/zenodo.292251</mods:url>
</mods:location>
<mods:classification id="7B3264C58E31378271BFE57ACB8780FC">book</mods:classification>
<mods:identifier id="DBC57A21011D2CB2FCAB660550C67A6D" type="Zenodo-Dep">292251</mods:identifier>
<mods:identifier id="8C3C9BF642DA6D11517813E2615EA555" type="DOI">10.5281/zenodo.292251</mods:identifier>
<mods:identifier id="A51491C6EDBEC9B984FC68B84191558B" type="ISBN">3-7643-0527-4</mods:identifier>
</mods:mods>
<treatment id="3A98448511120A61030B91D0991889D3" LSID="urn:lsid:plazi:treatment:3A98448511120A61030B91D0991889D3" httpUri="http://treatment.plazi.org/id/3A98448511120A61030B91D0991889D3" lastPageNumber="669" pageId="null" pageNumber="669" sec="euphorbiaceae.s38">
<title id="76AF11BEF6E6A686A64E4927DE68F32B" pageId="null" pageNumber="669">
<subSubSection id="0F563AEDD1E480CF28D868F6F311CF77" pageId="null" pageNumber="669" type="nomenclature">
<paragraph id="2DD8B6D53CA685A2760DF7BE53A95BDB" pageId="null" pageNumber="669">
<taxonomicName id="0801C84AE4A7434E72C36A12AE61E712" authority="L." class="Magnoliopsida" family="Euphorbiaceae" genus="Euphorbia" kingdom="Plantae" order="Malpighiales" pageId="null" pageNumber="669" phylum="Tracheophyta" rank="species" species="falcata">
<pageBreakToken id="0D44AD2A66CEABB90D7D708F19AE3062" pageId="null" pageNumber="669" start="start">Euphorbia</pageBreakToken>
<normalizedToken id="4C5DF0A1567BC3A53D60684AEFF3F608" originalValue="falcáta" pageId="null" pageNumber="669">falcata</normalizedToken>
<authorityName id="939D88A0765F6F4F2A96F1B45102EBDA" pageId="null" pageNumber="669">L.</authorityName>
</taxonomicName>
</paragraph>
</subSubSection>
<subSubSection id="2950409F179110478A38F033CB98DB46" pageId="null" pageNumber="669" type="vernacular_name">
<paragraph id="7CDA5614E8A774BFAEFD7AFD1A22FDF2" pageId="null" pageNumber="669">Sichel-Wolfsmilch</paragraph>
</subSubSection>
</title>
<subSubSection id="DC7B95383BB3ACC1EF4215E92F76BC91" pageId="null" pageNumber="669" type="description">
<paragraph id="0EEFB70BEF7FB5FFC831DF3F0941DBC5" pageId="null" pageNumber="669">
1 
<normalizedToken id="AB3C3BA4B5659324950D3DD0DF5EC919" originalValue="jährig" pageId="null" pageNumber="669">jaehrig</normalizedToken>
, mit einfacher Pfahlwurzel, kahl. Habitus wie 
<taxonomicName id="2C717E42628F4FEEC8F500C3505F2A6B" class="Magnoliopsida" family="Euphorbiaceae" genus="Euphorbia" kingdom="Plantae" order="Malpighiales" pageId="null" pageNumber="669" phylum="Tracheophyta" rank="species" species="exigua">
<emphasis id="0A2D4AB95897A76F58A1D0F51CE60A53" italics="true" pageId="null" pageNumber="669">E. exigua</emphasis>
</taxonomicName>
(Nr. 18). 
<normalizedToken id="9226CE1AD6AF7E2A68E949D7DCB2FC5A" originalValue="Stengelblätter" pageId="null" pageNumber="669">Stengelblaetter</normalizedToken>
<normalizedToken id="DA1156BA31EF260C66160E15D9625C17" originalValue="wechselständig" pageId="null" pageNumber="669">wechselstaendig</normalizedToken>
, stets vorzeitig abfallend, meist 
<normalizedToken id="E494F9FA88576E605F58B28BE4685A80" originalValue="spatelförmig" pageId="null" pageNumber="669">spatelfoermig</normalizedToken>
(selten die obersten lanzettlich), 0,5-2 cm lang, 2-4mal so lang wie breit, an der Spitze oft ausgerandet, ganzrandig, 
<emphasis id="FF39E0787FA5D63FE0D868448EA9E4FE" italics="true" pageId="null" pageNumber="669">sitzend;</emphasis>
<normalizedToken id="7279AB800625D4278E3DE488A1B79225" originalValue="Nebenblätter" pageId="null" pageNumber="669">Nebenblaetter</normalizedToken>
keine. 
<normalizedToken id="D85A20E4D8F209A76EA7243E1BB5A808" originalValue="Tragblätter" pageId="null" pageNumber="669">Tragblaetter</normalizedToken>
bei den 
<normalizedToken id="D13F0CA5C878665F32744E1638450096" originalValue="Einzelblütenständen" pageId="null" pageNumber="669">Einzelbluetenstaenden</normalizedToken>
nicht verwachsen, im 
<normalizedToken id="59D911FD5112B1BABA46255742140883" originalValue="Umriß" pageId="null" pageNumber="669">Umriss</normalizedToken>
fast 3eckig, etwa so lang wie breit, am Grunde breit abgerundet, steil in die durch den Mittelnerv gebildete, 0,5-1 mm 
<pageBreakToken id="B863F7C0231DAF14CE2A353901E4558D" pageId="null" pageNumber="669">lang</pageBreakToken>
ausgezogene Spitze 
<normalizedToken id="D28CD627A2DF144C42DD1B15A12A593A" originalValue="verschmälert" pageId="null" pageNumber="669">verschmaelert</normalizedToken>
. 
<normalizedToken id="C0C96E6D3E12D6E0C2781BFEBF9D855C" originalValue="Drüsen" pageId="null" pageNumber="669">Druesen</normalizedToken>
am 
<normalizedToken id="9EE8DEE3B1FBE8140D1780654C4CCFE5" originalValue="Hüllbecher" pageId="null" pageNumber="669">Huellbecher</normalizedToken>
gelb, mit 2 
<normalizedToken id="ED11D856025854D5CD3706E86C18E3E9" originalValue="weißen" pageId="null" pageNumber="669">weissen</normalizedToken>
, 
<normalizedToken id="4FAE73EDEE90E2390AE71D7C58AD75DB" originalValue="fadenförmigen" pageId="null" pageNumber="669">fadenfoermigen</normalizedToken>
<normalizedToken id="1FD0CAE427E3ABEDE003767CAC4F2158" originalValue="Anhängseln" pageId="null" pageNumber="669">Anhaengseln</normalizedToken>
. Frucht 2-2,5 mm lang, glatt. Samen 1,5-1,8 mm lang, 0,8-1,1 mm dick, 
<emphasis id="09057BBD68A3FDDF4F0FFD58001CEF0D" italics="true" pageId="null" pageNumber="669">
4kantig, auf allen 4 
<normalizedToken id="E4CB5AD2D1919EF9057A24F51B982192" originalValue="Flächen" pageId="null" pageNumber="669">Flaechen</normalizedToken>
mit 4-7 Querfurchen
</emphasis>
, grau oder rotbraun. - 
<normalizedToken id="1F06A6699FFE06BF614F07E8359D3044" originalValue="Blüte" pageId="null" pageNumber="669">Bluete</normalizedToken>
: Sommer bis Herbst.
</paragraph>
<paragraph id="322038A36442841B49A7D923F00AE77A" pageId="null" pageNumber="669">
<emphasis id="34C45BF35DAB2FBA4853B1D1C8CE7D9C" italics="true" pageId="null" pageNumber="669">Zytologische Angaben. 2n</emphasis>
= 
<emphasis id="065E18FD85FAA0B7DAA6DF5CB4270CF4" italics="true" pageId="null" pageNumber="669">16:</emphasis>
Material aus Ungarn (
<normalizedToken id="62C00EF42402BE781E4972E475274A4F" originalValue="Pólya" pageId="null" pageNumber="669">Polya</normalizedToken>
1958). 
<emphasis id="089F29EB721AB6FCD67AF9A812EB80AE" italics="true" pageId="null" pageNumber="669">2n</emphasis>
= 
<emphasis id="29D5D4AB025015064535F4287A09D2B9" italics="true" pageId="null" pageNumber="669">36:</emphasis>
Material aus Italien, normal sexuell (
<normalizedToken id="8F8595FC0FB22DDA7B15D7FAF32182A3" originalValue="D’Amato" pageId="null" pageNumber="669">D'Amato</normalizedToken>
1939).
</paragraph>
<paragraph id="37996375D90AA2788FF5269798A189A8" pageId="null" pageNumber="669">
<emphasis id="B438564B76DF7C90AD9B69A25F151870" italics="true" pageId="null" pageNumber="669">Standort.</emphasis>
Kollin. Kalkhaltige, 
<normalizedToken id="412DD8A55BA08395F4FAB37194A5B1E9" originalValue="nährstoffreiche" pageId="null" pageNumber="669">naehrstoffreiche</normalizedToken>
, lehmige 
<normalizedToken id="5653D46ED245C2B20DD098D0F5957266" originalValue="Böden" pageId="null" pageNumber="669">Boeden</normalizedToken>
. Unkrautgesellschaften in 
<normalizedToken id="7989E6BF5CD5DC7E9FB1774194DFBD1F" originalValue="Äckern" pageId="null" pageNumber="669">Aeckern</normalizedToken>
und auf 
<normalizedToken id="35C41D3FC991B5B70AC0414BE14AFA5D" originalValue="Schuttplätzen" pageId="null" pageNumber="669">Schuttplaetzen</normalizedToken>
.
</paragraph>
<paragraph id="68334D1E32B8346075A8F87C008D48DC" pageId="null" pageNumber="669">
<emphasis id="87A0A593E2214D0AAD9A734293600551" italics="true" pageId="null" pageNumber="669">Verbreitung.</emphasis>
<normalizedToken id="256FB9F43F2A5C27645E0AC3B695D2FC" originalValue="Ursprünglich" pageId="null" pageNumber="669">Urspruenglich</normalizedToken>
<emphasis id="AAF0E1D182ADD5A30FBC5344BE8860C1" italics="true" pageId="null" pageNumber="669">mediterran-westasiatische Pflanze;</emphasis>
heute weithin verschleppt. - Im Gebiet im Nordosten nicht vorhanden, sonst ziemlich verbreitet; selten.
</paragraph>
</subSubSection>
</treatment>
</document>